py_to_proto/__init__.py
py_to_proto/compat_annotated.py
py_to_proto/converter_base.py
py_to_proto/dataclass_to_proto.py
py_to_proto/descriptor_to_file.py
py_to_proto/descriptor_to_message_class.py
py_to_proto/json_to_service.py
py_to_proto/jtd_to_proto.py
py_to_proto/utils.py
py_to_proto/validation.py
jtd_to_proto-0.13.0.dist-info/LICENSE
jtd_to_proto-0.13.0.dist-info/METADATA
jtd_to_proto-0.13.0.dist-info/WHEEL
jtd_to_proto-0.13.0.dist-info/top_level.txt
jtd_to_proto-0.13.0.dist-info/RECORD
