Metadata-Version: 2.1
Name: jtd-to-proto
Version: 0.13.0
Summary: DEPRECATED: Please see py-to-proto: https://pypi.org/project/py-to-proto/
Home-page: https://github.com/IBM/py-to-proto
Author: Gabe Goodhart
Author-email: gabe.l.hart@gmail.com
License: MIT
Keywords: json,json typedef,jtd,protobuf,proto,dataclass
Platform: UNKNOWN
Classifier: Intended Audience :: Developers
Classifier: Programming Language :: Python :: 3
Classifier: Programming Language :: Python :: 3.7
Classifier: Programming Language :: Python :: 3.8
Classifier: Programming Language :: Python :: 3.9
Classifier: Programming Language :: Python :: 3.10
Classifier: Programming Language :: Python :: 3.11
License-File: LICENSE
Requires-Dist: protobuf (<5,>=3.19.0)
Requires-Dist: alchemy-logging (>=1.0.3)
Requires-Dist: typing-extensions (<5,>=4.5.0) ; python_version < "3.9"
